cimulate/__init__.py
cimulate/ecm.py
cimulate/elements.py
cimulate-0.1.2.dist-info/LICENSE
cimulate-0.1.2.dist-info/METADATA
cimulate-0.1.2.dist-info/WHEEL
cimulate-0.1.2.dist-info/top_level.txt
cimulate-0.1.2.dist-info/RECORD
