Metadata-Version: 2.1
Name: cimulate
Version: 0.1.2
Author-email: Knut Magnus Aasrud <km@aasrud.com>
License: GNU GENERAL PUBLIC LICENSE
Project-URL: Homepage, https://git.sr.ht/~kmaasrud/cimulate
Project-URL: Issues, https://todo.sr.ht/~kmaasrud/cimulate
Requires-Python: >=3.10
License-File: LICENSE
Requires-Dist: numpy ==2.1.1
Requires-Dist: scipy ==1.14.1
